CHANGES
LICENSE
MANIFEST.in
README.rst
requirements.txt
setup.py
Loslassa.egg-info/PKG-INFO
Loslassa.egg-info/SOURCES.txt
Loslassa.egg-info/dependency_links.txt
Loslassa.egg-info/entry_points.txt
Loslassa.egg-info/not-zip-safe
Loslassa.egg-info/requires.txt
Loslassa.egg-info/top_level.txt
loslassa/__init__.py
loslassa/__scratchpad.py
loslassa/_loslassa.py
loslassa/devserver.py
loslassa/utils.py