Metadata-Version: 1.1
Name: Loslassa
Version: 0.3.10
Summary: Just another toy static website generator
Home-page: http://github.com/obestwalter/loslassa/
Author: Oliver Bestwalter
Author-email: oliver@bestwalter.de
License: BSD
Platform: Unix
Classifier: Development Status :: 3 - Alpha
Classifier: Environment :: Console
Classifier: Intended Audience :: Other Audience
Classifier: License :: OSI Approved :: BSD License
Classifier: Operating System :: Unix
Classifier: Programming Language :: Python
Classifier: Programming Language :: Python :: 2.7
Classifier: Programming Language :: Python :: 3.4
Classifier: Topic :: Text Processing :: Markup :: HTML
Classifier: Topic :: Internet :: WWW/HTTP
